LICENSE
MANIFEST.in
README.md
makepw.py
makepw_test.py
setup.py
makepw.egg-info/PKG-INFO
makepw.egg-info/SOURCES.txt
makepw.egg-info/dependency_links.txt
makepw.egg-info/entry_points.txt
makepw.egg-info/top_level.txt