Metadata-Version: 2.1
Name: makepw
Version: 2.0.1
Summary: Generate unique, deterministic, and secure passwords.
Home-page: https://bitbucket.org/Omnifarious/MakePW
Author: Eric Hopper
Author-email: hopper@omnifarious.org
License: UNKNOWN
Platform: UNKNOWN
Classifier: Programming Language :: Python :: 2
Classifier: Programming Language :: Python :: 3
Classifier: Environment :: Console
Classifier: License :: OSI Approved :: GNU General Public License v3 or later (GPLv3+)
Classifier: Operating System :: OS Independent
Classifier: Development Status :: 5 - Production/Stable
Classifier: Topic :: Utilities
Classifier: Topic :: Security
Requires-Python: >=2.7
